tab_switch_counter/__init__.py
tab_switch_counter/example.py
tab_switch_counter/frontend/build/asset-manifest.json
tab_switch_counter/frontend/build/bootstrap.min.css
tab_switch_counter/frontend/build/index.html
tab_switch_counter/frontend/build/static/js/main.80f17556.js
tab_switch_counter/frontend/build/static/js/main.80f17556.js.LICENSE.txt
tab_switch_counter/frontend/build/static/js/main.80f17556.js.map
streamlit_tab_switch_counter-0.1.0.dist-info/LICENSE
streamlit_tab_switch_counter-0.1.0.dist-info/METADATA
streamlit_tab_switch_counter-0.1.0.dist-info/WHEEL
streamlit_tab_switch_counter-0.1.0.dist-info/top_level.txt
streamlit_tab_switch_counter-0.1.0.dist-info/RECORD
